app_min.py
nano_roman-0.1.1.dist-info/licenses/LICENSE
nano_roman-0.1.1.dist-info/METADATA
nano_roman-0.1.1.dist-info/WHEEL
nano_roman-0.1.1.dist-info/entry_points.txt
nano_roman-0.1.1.dist-info/top_level.txt
nano_roman-0.1.1.dist-info/RECORD
