Metadata-Version: 2.4
Name: nano-roman
Version: 0.1.1
Summary: Tiny Roman↔Decimal converter in ~1KB (zero deps)
Author: ozgunlu
License: MIT
Project-URL: Homepage, https://github.com/ozgunlu/nano-roman
Project-URL: Issues, https://github.com/ozgunlu/nano-roman/issues
Requires-Python: >=3.8
License-File: LICENSE
Dynamic: license-file
